MANIFEST.in
README.md
requirements.txt
setup.py
tests-requirements.txt
NGLessPy.egg-info/PKG-INFO
NGLessPy.egg-info/SOURCES.txt
NGLessPy.egg-info/dependency_links.txt
NGLessPy.egg-info/entry_points.txt
NGLessPy.egg-info/requires.txt
NGLessPy.egg-info/top_level.txt
cwl/ngl-types.yml
cwl/ngless-count.cwl
cwl/ngless-map.cwl
cwl/ngless-mapstats.cwl
cwl/ngless-select.cwl
cwl/ngless-trim.cwl
cwl/ngless-unique.cwl
cwl/workflow-example.cwl
ngless/NGLess.py
ngless/__init__.py
ngless/install.py
ngless/nglesspy_version.py
ngless/bin/__init__.py
ngless/bin/ngless_count.py
ngless/bin/ngless_install.py
ngless/bin/ngless_map.py
ngless/bin/ngless_mapstats.py
ngless/bin/ngless_select.py
ngless/bin/ngless_trim.py
ngless/bin/ngless_unique.py